ranger_cli/__init__.py
ranger_cli/cli.py
ranger_cli/cli_options.py
ranger_cli/cli_types.py
ranger_cli/client.py
ranger_cli/config.py
ranger_cli/utils.py
ranger_cli/version.py
ranger_cli/configure/__init__.py
ranger_cli/configure/commands.py
ranger_cli/plugins/__init__.py
ranger_cli/plugins/commands.py
ranger_cli/policy/__init__.py
ranger_cli/policy/commands.py
ranger_cli/service/__init__.py
ranger_cli/service/commands.py
ranger_cli/servicedef/__init__.py
ranger_cli/servicedef/commands.py
ranger_cli-0.0.1.dev0.dist-info/LICENSE
ranger_cli-0.0.1.dev0.dist-info/METADATA
ranger_cli-0.0.1.dev0.dist-info/WHEEL
ranger_cli-0.0.1.dev0.dist-info/entry_points.txt
ranger_cli-0.0.1.dev0.dist-info/top_level.txt
ranger_cli-0.0.1.dev0.dist-info/RECORD
